{
  "wedding": [
      {
        "id": 1,
        "title": "Photoshoot Package",
        "price": 900,
        "details": "This package includes pre-wedding and wedding day coverage."
      },
      {
        "id": 2,
        "title": "Videography Package",
        "price": 1400,
        "details": "This package includes wedding day coverage with a premium album."
      },
      {
        "id": 3,
        "title": "Combo Package",
        "price": 2000,
        "details": "This package includes full-day coverage, album, and a video highlight."
      }
  ],
  "graduation": {
    "title": "Graduation Package",
    "price": 120,
    "details":
      "Celebrate your graduation in style with our exclusive package, designed to make your special day unforgettable.",
    "label": "Hot"
  },
  "family": {
    "title": "Family Package",
    "price": 120,
    "details":
      "Celebrate your graduation in style with our exclusive package, designed to make your special day unforgettable.",
    "label": "Hot"
  },
  "birthday": {
    "title": "Birthday Package",
    "price": 120,
    "details":
      "Celebrate your graduation in style with our exclusive package, designed to make your special day unforgettable.",
    "label": "Hot"
  },
  "wedding packages": [
    {
      "id": 1,
      "title": "Photoshoot Package",
      "price": 120,
      "details":
        "Escape the ordinary of every day and discover the magic of destination weddings. A destination wedding is so much more than just one day."
    },
    {
      "id": 2,
      "title": "Videography Package",
      "price": 170,
      "details":
        "Experience an exclusive destination wedding package, crafted to create the perfect celebration of your love."
    },
    {
        "id": 3,
        "title": "Combo Package",
        "price": 150,
        "details":
          "Experience an exclusive destination wedding package, crafted to create the perfect celebration of your love."
      }
  ]

}